Workbook

Sheet Executive Summary
A1: LEANPILOT - BUSINESS PLAN
A3: Company Overview
A4: Company Name | B4: LeanPilot SRL
A5: Founded | B5: 2025
A6: Headquarters | B6: Italy (EU)
A7: Industry | B7: SaaS - Manufacturing Technology
A8: Website | B8: https://leanpilot.io
A10: Mission
B11: Democratize lean manufacturing for SME factories worldwide through AI-powered digital tools.
A13: Vision
B14: Become the global standard for digital lean management in factories with 10-500 employees.
A16: Value Proposition
B17: 17 integrated lean tools + AI copilot in one platform, replacing fragmented Excel/paper processes.
A19: Key Differentiators
A20: 1. | B20: All-in-one: OEE, TPM, SMED, VSM, 6S, CILT, Kaizen, A3, 5Why, Ishikawa, Pareto, Gemba, Andon + more
A21: 2. | B21: AI-powered Factory Copilot (lean-only, multilingual)
A22: 3. | B22: Lean Assessment wizard with personalized tool recommendations
A23: 4. | B23: Mobile-first, designed for shop floor use
A24: 5. | B24: GDPR + ePrivacy compliant (EU-first approach)
A26: Target Market
A27: Primary | B27: SME manufacturers (10-500 employees) in EU, Balkans, UK
A28: Secondary | B28: Lean consultants and training organizations
A29: Tertiary | B29: Large enterprises seeking departmental lean tools
A31: Business Model
A32: Type | B32: B2B SaaS - Monthly/Annual subscription
A33: Free Trial | B33: 14 days, full access, no credit card
A34: Pricing Tiers | B34: Starter / Professional / Business / Enterprise
A35: Revenue Streams | B35: Subscriptions, AI add-on, custom integrations, training

Sheet Market Analysis
A1: MARKET ANALYSIS
A3: Metric | B3: Value | C3: Basis | D3: Source
A4: Global Manufacturing SaaS TAM | B4: 50000000000 | C4: Global market size 2025 | D4: Source: Grand View Research, 2024
A5: EU SME Manufacturing SAM | B5: 2500000000 | C5: EU SME segment (~5% of TAM) | D5: Source: Eurostat SME data, 2024
A6: Lean-specific SOM (Year 5) | B6: =B5*0.005 | C6: Target 0.5% of SAM | D6: Calculated
A7: Target Factories (EU+Balkans) | B7: 180000 | C7: Factories 10-500 employees | D7: Source: Eurostat SBS, 2024
A8: Addressable (digital-ready) | B8: 54000 | C8: ~30% digital adoption rate | D8: Source: EU Digital Economy Index
A11: COMPETITOR LANDSCAPE
A12: Competitor | B12: Focus | C12: Pricing | D12: Weakness vs LeanPilot
A13: Tulip | B13: No-code manufacturing apps | C13: $250+/mo | D13: Complex setup, no lean methodology focus
A14: Poka | B14: Connected worker platform | C14: Enterprise only | D14: No lean tools, large enterprise focus
A15: Evocon | B15: OEE monitoring | C15: EUR99+/mo | D15: OEE-only, no problem-solving tools
A16: Parsable | B16: Digital work instructions | C16: Enterprise | D16: No lean assessment, no AI copilot
A17: MaintainX | B17: CMMS / maintenance | C17: $16+/user/mo | D17: Maintenance-only, no lean suite
A18: SafetyCulture | B18: Inspections & audits | C18: $24+/user/mo | D18: Audit-focused, not lean-specific
A19: Excel/Paper | B19: Manual lean tracking | C19: Free | D19: No automation, no analytics, error-prone
A22: SWOT ANALYSIS
A23: Strengths | B23: Weaknesses | C23: Opportunities | D23: Threats
A24: All-in-one lean suite (17 tools) | B24: New brand, no track record | C24: EU Green Deal driving lean adoption | D24: Large players adding lean modules
A25: AI-powered copilot | B25: Small initial team | C25: Post-COVID digital transformation | D25: Open-source lean tools emerging
A26: GDPR-first design | B26: Limited initial languages | C26: Balkans underserved market | D26: Economic downturn reducing IT spend
A27: Competitive pricing | B27: No mobile app (PWA only) | C27: Lean consulting partnerships | D27: Resistance to digital tools in SMEs
A28: Multilingual (EN/IT, expanding) | B28: Single cloud region initially | C28: Government digitization subsidies | D28: Data sovereignty concerns

Sheet Revenue Projections
A1: 5-YEAR REVENUE PROJECTIONS
A3: Metric | B3: Year 1 | C3: Year 2 | D3: Year 3 | E3: Year 4 | F3: Year 5
A4: New Customers (Starter) | B4: 40 | C4: 120 | D4: 280 | E4: 500 | F4: 750
A5: New Customers (Professional) | B5: 15 | C5: 60 | D5: 180 | E5: 350 | F5: 550
A6: New Customers (Business) | B6: 5 | C6: 25 | D6: 80 | E6: 180 | F6: 320
A7: New Customers (Enterprise) | B7: 1 | C7: 5 | D7: 15 | E7: 40 | F7: 80
A8: Total New Customers | B8: =SUM(B4:B7) | C8: =SUM(C4:C7) | D8: =SUM(D4:D7) | E8: =SUM(E4:E7) | F8: =SUM(F4:F7)
A9: Cumulative Customers | B9: =B8 | C9: =B9+C8 | D9: =C9+D8 | E9: =D9+E8 | F9: =E9+F8
A10: Churn Rate (Annual) | B10: 0.15 | C10: 0.12 | D10: 0.1 | E10: 0.08 | F10: 0.07
A11: Churned Customers | B11: =ROUND(B9*B10,0) | C11: =ROUND(B12*C10,0) | D11: =ROUND(C12*D10,0) | E11: =ROUND(D12*E10,0) | F11: =ROUND(E12*F10,0)
A12: Active Customers (End) | B12: =B9-B11 | C12: =C9-C11 | D12: =D9-D11 | E12: =E9-E11 | F12: =F9-F11
A14: PRICING (Monthly)
A15: Starter | B15: 49 | C15: 49 | D15: 59 | E15: 59 | F15: 69
A16: Professional | B16: 149 | C16: 149 | D16: 179 | E16: 179 | F16: 199
A17: Business | B17: 349 | C17: 349 | D17: 399 | E17: 399 | F17: 449
A18: Enterprise | B18: 899 | C18: 899 | D18: 999 | E18: 999 | F18: 1099
A20: MONTHLY RECURRING REVENUE
A21: MRR - Starter | B21: =B4*B15 | C21: =C4*C15 | D21: =D4*D15 | E21: =E4*E15 | F21: =F4*F15
A22: MRR - Professional | B22: =B5*B16 | C22: =C5*C16 | D22: =D5*D16 | E22: =E5*E16 | F22: =F5*F16
A23: MRR - Business | B23: =B6*B17 | C23: =C6*C17 | D23: =D6*D17 | E23: =E6*E17 | F23: =F6*F17
A24: MRR - Enterprise | B24: =B7*B18 | C24: =C7*C18 | D24: =D7*D18 | E24: =E7*E18 | F24: =F7*F18
A25: Total MRR | B25: =SUM(B21:B24) | C25: =SUM(C21:C24) | D25: =SUM(D21:D24) | E25: =SUM(E21:E24) | F25: =SUM(F21:F24)
A26: ARR (Annual Recurring Revenue) | B26: =B25*12 | C26: =C25*12 | D26: =D25*12 | E26: =E25*12 | F26: =F25*12
A28: ADDITIONAL REVENUE
A29: AI Copilot Add-on (20% uptake) | B29: =ROUND(B12*0.2*29*12,0) | C29: =ROUND(C12*0.2*29*12,0) | D29: =ROUND(D12*0.2*29*12,0) | E29: =ROUND(E12*0.2*29*12,0) | F29: =ROUND(F12*0.2*29*12,0)
A30: Training & Onboarding | B30: 5000 | C30: 20000 | D30: 60000 | E30: 120000 | F30: 200000
A31: Custom Integrations | B31: 0 | C31: 10000 | D31: 40000 | E31: 100000 | F31: 200000
A32: Total Additional Revenue | B32: =SUM(B29:B31) | C32: =SUM(C29:C31) | D32: =SUM(D29:D31) | E32: =SUM(E29:E31) | F32: =SUM(F29:F31)
A34: TOTAL ANNUAL REVENUE | B34: =B26+B32 | C34: =C26+C32 | D34: =D26+D32 | E34: =E26+E32 | F34: =F26+F32

Sheet Cost Structure
A1: 5-YEAR COST STRUCTURE
A3: Metric | B3: Year 1 | C3: Year 2 | D3: Year 3 | E3: Year 4 | F3: Year 5
A4: INFRASTRUCTURE
A5: Cloud Hosting (AWS/Vercel) | B5: 6000 | C5: 18000 | D5: 48000 | E5: 96000 | F5: 180000
A6: Database & Redis | B6: 2400 | C6: 6000 | D6: 14400 | E6: 28800 | F6: 48000
A7: OpenAI API Costs | B7: 3600 | C7: 12000 | D7: 36000 | E7: 84000 | F7: 156000
A8: Domain, SSL, CDN | B8: 500 | C8: 500 | D8: 1000 | E8: 1000 | F8: 2000
A9: Monitoring & Security | B9: 1200 | C9: 3600 | D9: 7200 | E9: 12000 | F9: 18000
A10: Subtotal Infrastructure | B10: =SUM(B5:B9) | C10: =SUM(C5:C9) | D10: =SUM(D5:D9) | E10: =SUM(E5:E9) | F10: =SUM(F5:F9)
A12: TEAM (Salaries + Benefits)
A13: Founders (2x) | B13: 0 | C13: 60000 | D13: 120000 | E13: 180000 | F13: 240000
A14: Backend Engineers | B14: 0 | C14: 45000 | D14: 135000 | E14: 225000 | F14: 360000
A15: Frontend Engineers | B15: 0 | C15: 45000 | D15: 90000 | E15: 180000 | F15: 270000
A16: DevOps / SRE | B16: 0 | C16: 0 | D16: 55000 | E16: 110000 | F16: 165000
A17: Product / Design | B17: 0 | C17: 0 | D17: 50000 | E17: 100000 | F17: 150000
A18: Sales & Marketing | B18: 0 | C18: 30000 | D18: 90000 | E18: 180000 | F18: 300000
A19: Customer Success | B19: 0 | C19: 0 | D19: 45000 | E19: 90000 | F19: 180000
A20: Subtotal Team | B20: =SUM(B13:B19) | C20: =SUM(C13:C19) | D20: =SUM(D13:D19) | E20: =SUM(E13:E19) | F20: =SUM(F13:F19)
A22: MARKETING & SALES
A23: Content Marketing & SEO | B23: 3000 | C23: 12000 | D23: 30000 | E23: 60000 | F23: 96000
A24: Paid Advertising | B24: 2000 | C24: 15000 | D24: 50000 | E24: 100000 | F24: 180000
A25: Events & Trade Shows | B25: 0 | C25: 5000 | D25: 20000 | E25: 40000 | F25: 60000
A26: Partner Commissions | B26: 0 | C26: 3000 | D26: 15000 | E26: 40000 | F26: 80000
A27: Subtotal Marketing | B27: =SUM(B23:B26) | C27: =SUM(C23:C26) | D27: =SUM(D23:D26) | E27: =SUM(E23:E26) | F27: =SUM(F23:F26)
A29: OPERATIONS
A30: Legal & Compliance | B30: 3000 | C30: 6000 | D30: 12000 | E30: 18000 | F30: 24000
A31: Accounting & Admin | B31: 2000 | C31: 5000 | D31: 10000 | E31: 18000 | F31: 24000
A32: Insurance | B32: 1500 | C32: 3000 | D32: 6000 | E32: 10000 | F32: 15000
A33: Office / Coworking | B33: 0 | C33: 6000 | D33: 12000 | E33: 24000 | F33: 36000
A34: Subtotal Operations | B34: =SUM(B30:B33) | C34: =SUM(C30:C33) | D34: =SUM(D30:D33) | E34: =SUM(E30:E33) | F34: =SUM(F30:F33)
A36: TOTAL COSTS | B36: =B10+B20+B27+B34 | C36: =C10+C20+C27+C34 | D36: =D10+D20+D27+D34 | E36: =E10+E20+E27+E34 | F36: =F10+F20+F27+F34
A37: Revenue (from Projections) | B37: ='Revenue Projections'!B34 | C37: ='Revenue Projections'!C34 | D37: ='Revenue Projections'!D34 | E37: ='Revenue Projections'!E34 | F37: ='Revenue Projections'!F34
A38: NET PROFIT / (LOSS) | B38: =B37-B36 | C38: =C37-C36 | D38: =D37-D36 | E38: =E37-E36 | F38: =F37-F36
A39: Profit Margin | B39: =IF(B37=0,0,B38/B37) | C39: =IF(C37=0,0,C38/C37) | D39: =IF(D37=0,0,D38/D37) | E39: =IF(E37=0,0,E38/E37) | F39: =IF(F37=0,0,F38/F37)

Sheet Pricing Strategy
A1: PRICING STRATEGY & FEATURE MATRIX
A3: Feature / Capability | B3: Starter $49/mo | C3: Professional $149/mo | D3: Business $349/mo | E3: Enterprise $899/mo
A4: CORE LEAN TOOLS
A5: OEE Dashboard | B5: Basic | C5: Advanced | D5: Advanced | E5: Custom
A6: Production Input | B6: Yes | C6: Yes | D6: Yes | E6: Yes
A7: Hourly Production Board | B7: Yes | C7: Yes | D7: Yes | E7: Yes
A8: Andon Board | B8: - | C8: Yes | D8: Yes | E8: Yes
A9: 6S Audit | B9: Yes | C9: Yes | D9: Yes | E9: Yes
A10: CILT Checklist | B10: - | C10: Yes | D10: Yes | E10: Yes
A11: TPM Dashboard | B11: - | C11: Yes | D11: Yes | E11: Yes
A13: PROBLEM SOLVING
A14: 5 Why Analysis | B14: Yes | C14: Yes | D14: Yes | E14: Yes
A15: Ishikawa Diagram | B15: Yes | C15: Yes | D15: Yes | E15: Yes
A16: Pareto Chart | B16: - | C16: Yes | D16: Yes | E16: Yes
A17: A3 Report | B17: - | C17: Yes | D17: Yes | E17: Yes
A19: IMPROVEMENT
A20: Kaizen Board | B20: - | C20: Yes | D20: Yes | E20: Yes
A21: Value Stream Mapping | B21: - | C21: - | D21: Yes | E21: Yes
A22: SMED Tracker | B22: - | C22: - | D22: Yes | E22: Yes
A23: Gemba Walk | B23: - | C23: Yes | D23: Yes | E23: Yes
A25: AI & ANALYTICS
A26: Factory Copilot (AI) | B26: - | C26: Basic | D26: Advanced | E26: Unlimited
A27: Lean Assessment | B27: Yes | C27: Yes | D27: Yes | E27: Yes
A28: Custom Reports | B28: - | C28: - | D28: Yes | E28: Yes
A29: API Access | B29: - | C29: - | D29: - | E29: Yes
A31: SUPPORT & ADMIN
A32: Users Included | B32: 3 | C32: 10 | D32: 25 | E32: Unlimited
A33: Production Lines | B33: 1 | C33: 3 | D33: 10 | E33: Unlimited
A34: Data Retention | B34: 90 days | C34: 1 year | D34: 3 years | E34: Unlimited
A35: Support | B35: Email | C35: Priority | D35: Dedicated | E35: 24/7 + SLA
A36: Onboarding | B36: Self-serve | C36: Guided | D36: White-glove | E36: Custom
A37: SSO / SAML | B37: - | C37: - | D37: Yes | E37: Yes
A38: Custom Branding | B38: - | C38: - | D38: - | E38: Yes

Sheet Go-to-Market
A1: GO-TO-MARKET STRATEGY
A3: Phase | B3: Timeline | C3: Activities | D3: Budget | E3: KPIs
A4: Phase 1: Validate | B4: Months 1-6 | C4: Beta launch with 10-20 Italian factories Content marketing (lean blog, LinkedIn) Lean consultant partnerships Product-market fit validation | D4: $15,000 | E4: 20 beta users 5 paying customers NPS > 40
A5: Phase 2: Scale EU | B5: Months 7-18 | C5: Launch in IT, DE, UK, Balkans Paid ads (Google, LinkedIn) Trade show presence (SPS, Hannover) Partner channel development Localize for DE, FR | D5: $120,000 | E5: 200 customers $50K MRR CAC < $500
A6: Phase 3: Expand | B6: Months 19-36 | C6: Enter US market Enterprise sales team Strategic partnerships (ERP vendors) Advanced AI features Mobile app launch | D6: $500,000 | E6: 1,000 customers $300K MRR LTV/CAC > 3
A7: Phase 4: Dominate | B7: Months 37-60 | C7: Market leadership in EU Acquisition targets IPO preparation Platform ecosystem Marketplace for lean add-ons | D7: $1,500,000 | E7: 3,000+ customers $1M+ MRR Profitable

Sheet KPIs & Milestones
A1: KEY PERFORMANCE INDICATORS & MILESTONES
A3: Metric | B3: Year 1 | C3: Year 2 | D3: Year 3 | E3: Year 4 | F3: Year 5
A4: GROWTH METRICS
A5: Active Customers | B5: ='Revenue Projections'!B12 | C5: ='Revenue Projections'!C12 | D5: ='Revenue Projections'!D12 | E5: ='Revenue Projections'!E12 | F5: ='Revenue Projections'!F12
A6: MRR | B6: ='Revenue Projections'!B25 | C6: ='Revenue Projections'!C25 | D6: ='Revenue Projections'!D25 | E6: ='Revenue Projections'!E25 | F6: ='Revenue Projections'!F25
A7: ARR | B7: ='Revenue Projections'!B26 | C7: ='Revenue Projections'!C26 | D7: ='Revenue Projections'!D26 | E7: ='Revenue Projections'!E26 | F7: ='Revenue Projections'!F26
A8: YoY Revenue Growth | B8: N/A | C8: =IF(B7=0,0,(C7-B7)/B7) | D8: =IF(C7=0,0,(D7-C7)/C7) | E8: =IF(D7=0,0,(E7-D7)/D7) | F8: =IF(E7=0,0,(F7-E7)/E7)
A10: UNIT ECONOMICS
A11: ARPU (Monthly) | B11: 49 | C11: 95 | D11: 145 | E11: 185 | F11: 220
A12: CAC (Customer Acquisition Cost) | B12: 800 | C12: 500 | D12: 400 | E12: 350 | F12: 300
A13: LTV (Lifetime Value) | B13: =IF(B17=0,0,B11/(B17)) | C13: =IF(C17=0,0,C11/(C17)) | D13: =IF(D17=0,0,D11/(D17)) | E13: =IF(E17=0,0,E11/(E17)) | F13: =IF(F17=0,0,F11/(F17))
A14: LTV/CAC Ratio | B14: =IF(B12=0,0,B13/B12) | C14: =IF(C12=0,0,C13/C12) | D14: =IF(D12=0,0,D13/D12) | E14: =IF(E12=0,0,E13/E12) | F14: =IF(F12=0,0,F13/F12)
A15: Payback Period (Months) | B15: =IF(B11=0,0,B12/B11) | C15: =IF(C11=0,0,C12/C11) | D15: =IF(D11=0,0,D12/D11) | E15: =IF(E11=0,0,E12/E11) | F15: =IF(F11=0,0,F12/F11)
A17: OPERATIONAL
A18: Monthly Churn Rate | B18: 0.013 | C18: 0.01 | D18: 0.008 | E18: 0.007 | F18: 0.006
A19: NPS Score | B19: 30 | C19: 45 | D19: 55 | E19: 60 | F19: 65
A20: Support Tickets/Customer/Mo | B20: 2.5 | C20: 1.8 | D20: 1.2 | E20: 0.8 | F20: 0.5
A21: Uptime SLA | B21: 0.995 | C21: 0.999 | D21: 0.999 | E21: 0.9999 | F21: 0.9999
A24: KEY MILESTONES
A25: Q2 2025 | B25: Beta launch with 10 Italian pilot factories
A26: Q4 2025 | B26: First 50 paying customers, break-even on infrastructure
A27: Q2 2026 | B27: Launch in Germany and UK, 200 customers
A28: Q4 2026 | B28: Reach $50K MRR, close seed round
A29: Q2 2027 | B29: 500 customers, mobile app launch
A30: Q4 2027 | B30: Reach $300K MRR, Series A ready
A31: 2028 | B31: 1,000+ customers, US expansion
A32: 2029 | B32: Market leader in EU SME lean SaaS, $1M+ MRR
A33: 2030 | B33: 3,000+ customers, profitability, IPO/exit preparation
